libertai_unstoppable_denver_agents/__init__.py
libertai_unstoppable_denver_agents/abis/uniswap_router.json
libertai_unstoppable_denver_agents/abis/uniswap_v3_pool.json
libertai_unstoppable_denver_agents/constants.py
libertai_unstoppable_denver_agents/interfaces.py
libertai_unstoppable_denver_agents/main.py
libertai_unstoppable_denver_agents/provider.py
libertai_unstoppable_denver_agents/utils.py
libertai_unstoppable_denver_agents-0.0.8.dist-info/METADATA
libertai_unstoppable_denver_agents-0.0.8.dist-info/WHEEL
libertai_unstoppable_denver_agents-0.0.8.dist-info/RECORD
