Metadata-Version: 2.3
Name: libertai-unstoppable-denver-agents
Version: 0.0.8
Summary: Wrapper of LibertAI's AI Agents framework to add autonomous behavior (pay for their own computing)
Author: Reza Rahemtola
Author-email: contact@rezar.fr
Requires-Python: >=3.10,<3.13
Classifier: Programming Language :: Python :: 3
Classifier: Programming Language :: Python :: 3.10
Classifier: Programming Language :: Python :: 3.11
Classifier: Programming Language :: Python :: 3.12
Requires-Dist: coinbase-agentkit (>=0.1.3,<0.2.0)
Requires-Dist: coinbase-agentkit-langchain (>=0.1.0,<0.2.0)
Requires-Dist: libertai-agents (>=0.1.5,<0.2.0)
